README.rst
setup.py
Flask_Compressor.egg-info/PKG-INFO
Flask_Compressor.egg-info/SOURCES.txt
Flask_Compressor.egg-info/dependency_links.txt
Flask_Compressor.egg-info/not-zip-safe
Flask_Compressor.egg-info/requires.txt
Flask_Compressor.egg-info/top_level.txt
flask_compressor/__init__.py
flask_compressor/blueprint.py
flask_compressor/processors.py
flask_compressor/templating.py