Metadata-Version: 1.1
Name: Flask-Compressor
Version: 0.1.1
Summary: Compress your CSS and JS files.
Home-page: https://github.com/lmeunier/flask-compressor
Author: Laurent Meunier
Author-email: laurent@deltalima.net
License: UNKNOWN
Platform: UNKNOWN
Classifier: Development Status :: 4 - Beta
Classifier: Environment :: Web Environment
Classifier: Intended Audience :: Developers
Classifier: License :: OSI Approved :: BSD License
Classifier: Operating System :: OS Independent
Classifier: Programming Language :: Python
Classifier: Topic :: Internet :: WWW/HTTP :: Dynamic Content
Classifier: Topic :: Software Development :: Libraries :: Python Modules
